{
	"info": {
		"_postman_id": "5e582fec-2a21-489e-8584-3861064fe19d",
		"name": "New Collection",
		"schema": "https://schema.getpostman.com/json/collection/v2.1.0/collection.json",
		"_exporter_id": "6611406",
		"_collection_link": "https://interstellar-firefly-388712.postman.co/workspace/Team-Workspace~a1213082-0ee8-43cc-85f3-6d82d8e3bee8/collection/6611406-5e582fec-2a21-489e-8584-3861064fe19d?action=share&source=collection_link&creator=6611406"
	},
	"item": [
		{
			"name": "data-rest-mongo",
			"item": [
				{
					"name": "all-urls",
					"request": {
						"method": "GET",
						"header": [],
						"url": {
							"raw": "http://localhost:8080",
							"protocol": "http",
							"host": [
								"localhost"
							],
							"port": "8080"
						}
					},
					"response": []
				},
				{
					"name": "profile",
					"request": {
						"method": "GET",
						"header": [],
						"url": {
							"raw": "http://localhost:8080/profile/people",
							"protocol": "http",
							"host": [
								"localhost"
							],
							"port": "8080",
							"path": [
								"profile",
								"people"
							]
						}
					},
					"response": []
				},
				{
					"name": "profile-people",
					"request": {
						"method": "GET",
						"header": [],
						"url": {
							"raw": "http://localhost:8080/profile/people",
							"protocol": "http",
							"host": [
								"localhost"
							],
							"port": "8080",
							"path": [
								"profile",
								"people"
							]
						}
					},
					"response": []
				},
				{
					"name": "people",
					"request": {
						"method": "GET",
						"header": [],
						"url": {
							"raw": "http://localhost:8080/people",
							"protocol": "http",
							"host": [
								"localhost"
							],
							"port": "8080",
							"path": [
								"people"
							]
						}
					},
					"response": []
				},
				{
					"name": "people",
					"request": {
						"method": "POST",
						"header": [],
						"body": {
							"mode": "raw",
							"raw": "{\r\n    \"firstName\": \"Frodo\",\r\n    \"lastName\": \"Baggins\"\r\n}",
							"options": {
								"raw": {
									"language": "json"
								}
							}
						},
						"url": {
							"raw": "http://localhost:8080/people",
							"protocol": "http",
							"host": [
								"localhost"
							],
							"port": "8080",
							"path": [
								"people"
							]
						}
					},
					"response": []
				},
				{
					"name": "person",
					"request": {
						"method": "GET",
						"header": [],
						"url": {
							"raw": "http://localhost:8080/people/6700f99047523b458c378bc1",
							"protocol": "http",
							"host": [
								"localhost"
							],
							"port": "8080",
							"path": [
								"people",
								"6700f99047523b458c378bc1"
							]
						}
					},
					"response": []
				},
				{
					"name": "search",
					"request": {
						"method": "GET",
						"header": [],
						"url": {
							"raw": "http://localhost:8080/people/search/findByLastName?name=Baggins",
							"protocol": "http",
							"host": [
								"localhost"
							],
							"port": "8080",
							"path": [
								"people",
								"search",
								"findByLastName"
							],
							"query": [
								{
									"key": "name",
									"value": "Baggins"
								}
							]
						}
					},
					"response": []
				},
				{
					"name": "update",
					"request": {
						"method": "PUT",
						"header": [],
						"body": {
							"mode": "raw",
							"raw": "{\r\n    \"firstName\": \"Rohit\",\r\n    \"lastName\": \"Nandi\"\r\n}",
							"options": {
								"raw": {
									"language": "json"
								}
							}
						},
						"url": {
							"raw": "http://localhost:8080/people/6700f99047523b458c378bc1",
							"protocol": "http",
							"host": [
								"localhost"
							],
							"port": "8080",
							"path": [
								"people",
								"6700f99047523b458c378bc1"
							]
						}
					},
					"response": []
				},
				{
					"name": "person",
					"request": {
						"method": "PATCH",
						"header": [],
						"body": {
							"mode": "raw",
							"raw": "{\r\n    \"firstName\": \"Rup\"\r\n}",
							"options": {
								"raw": {
									"language": "json"
								}
							}
						},
						"url": {
							"raw": "http://localhost:8080/people/6700f99047523b458c378bc1",
							"protocol": "http",
							"host": [
								"localhost"
							],
							"port": "8080",
							"path": [
								"people",
								"6700f99047523b458c378bc1"
							]
						}
					},
					"response": []
				},
				{
					"name": "person",
					"request": {
						"method": "DELETE",
						"header": [],
						"url": {
							"raw": "http://localhost:8080/people/6700f99047523b458c378bc1",
							"protocol": "http",
							"host": [
								"localhost"
							],
							"port": "8080",
							"path": [
								"people",
								"6700f99047523b458c378bc1"
							]
						}
					},
					"response": []
				}
			]
		}
	]
}